{
  "moon": [
    {
      "id": "rt-r1-1",
      "points": "0 80 0 0 40 40"
    },
    {
      "id": "rt-r1-2",
      "points": "40 80 40 0 80 40"
    },
    {
      "id": "rt-r1-3",
      "points": "80 80 80 0 120 40"
    },
    {
      "id": "rt-r1-4",
      "points": "120 80 120 0 160 40"
    },
    {
      "id": "rt-r1-5",
      "points": "160 80 160 0 200 40"
    },
    {
      "id": "rt-r1-6",
      "points": "200 80 200 0 240 40"
    },
    {
      "id": "rt-r1-7",
      "points": "240 80 240 0 280 40"
    },
    {
      "id": "rt-r1-8",
      "points": "280 80 280 0 320 40"
    },
    {
      "id": "rt-r1-9",
      "points": "320 80 320 0 360 40"
    },
    {
      "id": "rt-r1-10",
      "points": "360 80 360 0 400 40"
    },
    {
      "id": "rt-r2-1",
      "points": "0 160 0 80 40 120"
    },
    {
      "id": "rt-r2-2",
      "points": "40 160 40 80 80 120"
    },
    {
      "id": "rt-r2-3",
      "points": "80 160 80 80 120 120"
    },
    {
      "id": "rt-r2-4",
      "points": "120 160 120 80 160 120"
    },
    {
      "id": "rt-r2-5",
      "points": "160 160 160 80 200 120"
    },
    {
      "id": "rt-r2-6",
      "points": "200 160 200 80 240 120"
    },
    {
      "id": "rt-r2-7",
      "points": "240 160 240 80 280 120"
    },
    {
      "id": "rt-r2-8",
      "points": "280 160 280 80 320 120"
    },
    {
      "id": "rt-r2-9",
      "points": "320 160 320 80 360 120"
    },
    {
      "id": "rt-r2-10",
      "points": "360 160 360 80 400 120"
    },
    {
      "id": "rt-r3-1",
      "points": "0 240 0 160 40 200"
    },
    {
      "id": "rt-r3-2",
      "points": "40 240 40 160 80 200"
    },
    {
      "id": "rt-r3-3",
      "points": "80 240 80 160 120 200"
    },
    {
      "id": "rt-r3-4",
      "points": "120 240 120 160 160 200"
    },
    {
      "id": "rt-r3-5",
      "points": "160 240 160 160 200 200"
    },
    {
      "id": "rt-r3-6",
      "points": "200 240 200 160 240 200"
    },
    {
      "id": "rt-r3-7",
      "points": "240 240 240 160 280 200"
    },
    {
      "id": "rt-r3-8",
      "points": "280 240 280 160 320 200"
    },
    {
      "id": "rt-r3-9",
      "points": "320 240 320 160 360 200"
    },
    {
      "id": "rt-r3-10",
      "points": "360 240 360 160 400 200"
    },
    {
      "id": "rt-r4-1",
      "points": "0 320 0 240 40 280"
    },
    {
      "id": "rt-r4-2",
      "points": "40 320 40 240 80 280"
    },
    {
      "id": "rt-r4-3",
      "points": "80 320 80 240 120 280"
    },
    {
      "id": "rt-r4-4",
      "points": "120 320 120 240 160 280"
    },
    {
      "id": "rt-r4-5",
      "points": "160 320 160 240 200 280"
    },
    {
      "id": "rt-r4-6",
      "points": "200 320 200 240 240 280"
    },
    {
      "id": "rt-r4-7",
      "points": "240 320 240 240 280 280"
    },
    {
      "id": "rt-r4-8",
      "points": "280 320 280 240 320 280"
    },
    {
      "id": "rt-r4-9",
      "points": "320 320 320 240 360 280"
    },
    {
      "id": "rt-r4-10",
      "points": "360 320 360 240 400 280"
    },
    {
      "id": "rt-r5-1",
      "points": "0 400 0 320 40 360"
    },
    {
      "id": "rt-r5-2",
      "points": "40 400 40 320 80 360"
    },
    {
      "id": "rt-r5-3",
      "points": "80 400 80 320 120 360"
    },
    {
      "id": "rt-r5-4",
      "points": "120 400 120 320 160 360"
    },
    {
      "id": "rt-r5-5",
      "points": "160 400 160 320 200 360"
    },
    {
      "id": "rt-r5-6",
      "points": "200 400 200 320 240 360"
    },
    {
      "id": "rt-r5-7",
      "points": "240 400 240 320 280 360"
    },
    {
      "id": "rt-r5-8",
      "points": "280 400 280 320 320 360"
    },
    {
      "id": "rt-r5-9",
      "points": "320 400 320 320 360 360"
    },
    {
      "id": "rt-r5-10",
      "points": "360 400 360 320 400 360"
    },
    {
      "id": "lt-r1-1",
      "points": "40 -40 40 40 0 0"
    },
    {
      "id": "lt-r1-2",
      "points": "80 -40 80 40 40 0"
    },
    {
      "id": "lt-r1-3",
      "points": "120 -40 120 40 80 0"
    },
    {
      "id": "lt-r1-4",
      "points": "160 -40 160 40 120 0"
    },
    {
      "id": "lt-r1-5",
      "points": "200 -40 200 40 160 0"
    },
    {
      "id": "lt-r1-6",
      "points": "240 -40 240 40 200 0"
    },
    {
      "id": "lt-r1-7",
      "points": "280 -40 280 40 240 0"
    },
    {
      "id": "lt-r1-8",
      "points": "320 -40 320 40 280 0"
    },
    {
      "id": "lt-r1-9",
      "points": "360 -40 360 40 320 0"
    },
    {
      "id": "lt-r1-10",
      "points": "400 -40 400 40 360 0"
    },
    {
      "id": "lt-r2-1",
      "points": "40 40 40 120 0 80"
    },
    {
      "id": "lt-r2-2",
      "points": "80 40 80 120 40 80"
    },
    {
      "id": "lt-r2-3",
      "points": "120 40 120 120 80 80"
    },
    {
      "id": "lt-r2-4",
      "points": "160 40 160 120 120 80"
    },
    {
      "id": "lt-r2-5",
      "points": "200 40 200 120 160 80"
    },
    {
      "id": "lt-r2-6",
      "points": "240 40 240 120 200 80"
    },
    {
      "id": "lt-r2-7",
      "points": "280 40 280 120 240 80"
    },
    {
      "id": "lt-r2-8",
      "points": "320 40 320 120 280 80"
    },
    {
      "id": "lt-r2-9",
      "points": "360 40 360 120 320 80"
    },
    {
      "id": "lt-r2-10",
      "points": "400 40 400 120 360 80"
    },
    {
      "id": "lt-r3-1",
      "points": "40 120 40 200 0 160"
    },
    {
      "id": "lt-r3-2",
      "points": "80 120 80 200 40 160"
    },
    {
      "id": "lt-r3-3",
      "points": "120 120 120 200 80 160"
    },
    {
      "id": "lt-r3-4",
      "points": "160 120 160 200 120 160"
    },
    {
      "id": "lt-r3-5",
      "points": "200 120 200 200 160 160"
    },
    {
      "id": "lt-r3-6",
      "points": "240 120 240 200 200 160"
    },
    {
      "id": "lt-r3-7",
      "points": "280 120 280 200 240 160"
    },
    {
      "id": "lt-r3-8",
      "points": "320 120 320 200 280 160"
    },
    {
      "id": "lt-r3-9",
      "points": "360 120 360 200 320 160"
    },
    {
      "id": "lt-r3-10",
      "points": "400 120 400 200 360 160"
    },
    {
      "id": "lt-r4-1",
      "points": "40 200 40 280 0 240"
    },
    {
      "id": "lt-r4-2",
      "points": "80 200 80 280 40 240"
    },
    {
      "id": "lt-r4-3",
      "points": "120 200 120 280 80 240"
    },
    {
      "id": "lt-r4-4",
      "points": "160 200 160 280 120 240"
    },
    {
      "id": "lt-r4-5",
      "points": "200 200 200 280 160 240"
    },
    {
      "id": "lt-r4-6",
      "points": "240 200 240 280 200 240"
    },
    {
      "id": "lt-r4-7",
      "points": "280 200 280 280 240 240"
    },
    {
      "id": "lt-r4-8",
      "points": "320 200 320 280 280 240"
    },
    {
      "id": "lt-r4-9",
      "points": "360 200 360 280 320 240"
    },
    {
      "id": "lt-r4-10",
      "points": "400 200 400 280 360 240"
    },
    {
      "id": "lt-r5-1",
      "points": "40 280 40 360 0 320"
    },
    {
      "id": "lt-r5-2",
      "points": "80 280 80 360 40 320"
    },
    {
      "id": "lt-r5-3",
      "points": "120 280 120 360 80 320"
    },
    {
      "id": "lt-r5-4",
      "points": "160 280 160 360 120 320"
    },
    {
      "id": "lt-r5-6",
      "points": "240 280 240 360 200 320"
    },
    {
      "id": "lt-r5-5",
      "points": "200 280 200 360 160 320"
    },
    {
      "id": "lt-r5-7",
      "points": "280 280 280 360 240 320"
    },
    {
      "id": "lt-r5-8",
      "points": "320 280 320 360 280 320"
    },
    {
      "id": "lt-r5-9",
      "points": "360 280 360 360 320 320"
    },
    {
      "id": "lt-r5-10",
      "points": "400 280 400 360 360 320"
    },
    {
      "id": "lt-r6-1",
      "points": "40 360 40 440 0 400"
    },
    {
      "id": "lt-r6-2",
      "points": "80 360 80 440 40 400"
    },
    {
      "id": "lt-r6-3",
      "points": "120 360 120 440 80 400"
    },
    {
      "id": "lt-r6-4",
      "points": "160 360 160 440 120 400"
    },
    {
      "id": "lt-r6-5",
      "points": "200 360 200 440 160 400"
    },
    {
      "id": "lt-r6-6",
      "points": "240 360 240 440 200 400"
    },
    {
      "id": "lt-r6-7",
      "points": "280 360 280 440 240 400"
    },
    {
      "id": "lt-r6-8",
      "points": "320 360 320 440 280 400"
    },
    {
      "id": "lt-r6-9",
      "points": "360 360 360 440 320 400"
    },
    {
      "id": "lt-r6-10",
      "points": "400 360 400 440 360 400"
    }
  ]
}
